Presente/Programa.py
Presente/__init__.py
Presente/variablesGlobales.py
Presente/base/__init__.py
Presente/configuracion/__init__.py
Presente/grafica/Graphics.py
Presente/grafica/Language.py
Presente/grafica/Menu.py
Presente/grafica/__init__.py
Presente/grafica/imagenes_rc.py
Presente/grafica/audio/__init__.py
Presente/grafica/audio/saludos/__init__.py
Presente/grafica/audio/temp/__init__.py
Presente/grafica/imagen/__init__.py
Presente/grafica/maestra/CardStudent.py
Presente/grafica/maestra/Help.py
Presente/grafica/maestra/ModifyStudent.py
Presente/grafica/maestra/PassList.py
Presente/grafica/maestra/QueryStudent.py
Presente/grafica/maestra/StudentTab.py
Presente/grafica/maestra/Students.py
Presente/grafica/maestra/__init__.py
Presente/grafica/temp/__init__.py
Presente/grafica/template/__init__.py
Presente/grafica/ui/__init__.py
Presente/idioma/__init__.py
Presente/logica/Audio.py
Presente/logica/ClassRoom.py
Presente/logica/Date.py
Presente/logica/Email.py
Presente/logica/PDF.py
Presente/logica/PDFActas.py
Presente/logica/PDFStudent.py
Presente/logica/Protocol.py
Presente/logica/QR.py
Presente/logica/Student.py
Presente/logica/System.py
Presente/logica/Usefull.py
Presente/logica/__init__.py
Presente/pdf/__init__.py
Presente/pdf/ficha/__init__.py
Presente/persistencia/Connection.py
Presente/persistencia/Mapper.py
Presente/persistencia/MapperTest.py
Presente/persistencia/__init__.py
Presente/testing/TestEjecutar.py
Presente/testing/TestEmail.py
Presente/testing/TestList.py
Presente/testing/TestPassList.py
Presente/testing/TestQR.py
Presente/testing/TestStudent.py
Presente/testing/TestUsefull.py
Presente/testing/__init__.py
Presente-8.0.dist-info/METADATA
Presente-8.0.dist-info/WHEEL
Presente-8.0.dist-info/top_level.txt
Presente-8.0.dist-info/RECORD
