Metadata-Version: 2.1
Name: Presente
Version: 8.0
Summary: Programa para listar presente en clase
Home-page: UNKNOWN
Author: Bravo India Tango
Author-email: bravo.india.tango2019@gmail.com
License: GPL
Keywords: school,QR,PDF
Platform: UNKNOWN
Classifier: Topic :: Education :: Computer Aided Instruction (CAI)
Classifier: License :: Free For Educational Use
Classifier: Intended Audience :: Education
Classifier: Programming Language :: Python :: 3.7
Classifier: Natural Language :: Spanish
Requires-Dist: PyQt5
Requires-Dist: pygame
Requires-Dist: numpy
Requires-Dist: fpdf
Requires-Dist: pyzbar
Requires-Dist: qrcode
